yt_mpv/__init__.py
yt_mpv/__main__.py
yt_mpv/launcher.py
yt_mpv/player.py
yt_mpv/archive/__init__.py
yt_mpv/archive/archive_org.py
yt_mpv/archive/yt_dlp.py
yt_mpv/cli/__init__.py
yt_mpv/cli/args.py
yt_mpv/cli/commands.py
yt_mpv/cli/main.py
yt_mpv/install/__init__.py
yt_mpv/install/bookmarklet.py
yt_mpv/install/desktop.py
yt_mpv/install/setup.py
yt_mpv/utils/__init__.py
yt_mpv/utils/cache.py
yt_mpv/utils/config.py
yt_mpv/utils/fs.py
yt_mpv/utils/notify.py
yt_mpv/utils/url.py
yt_mpv-0.2.7.dist-info/entry_points.txt
yt_mpv-0.2.7.dist-info/licenses/LICENSE.md
yt_mpv-0.2.7.dist-info/WHEEL
yt_mpv-0.2.7.dist-info/METADATA
yt_mpv-0.2.7.dist-info/RECORD
