Metadata-Version: 2.4
Name: yt-mpv
Version: 0.2.7
Summary: Play videos in MPV, while archiving them on archive.org
Author-email: Gareth Davidson <gaz@bitplane.net>
License-File: LICENSE.md
Requires-Dist: uv
Requires-Dist: internetarchive
Requires-Dist: freeze_one~=0.2
Requires-Dist: flake8 ; extra == "dev"
Requires-Dist: pre-commit ; extra == "dev"
Requires-Dist: pytest ; extra == "dev"
Requires-Dist: coverage ; extra == "dev"
Requires-Dist: pytest-cov ; extra == "dev"
Requires-Dist: build ; extra == "dev"
Requires-Dist: twine ; extra == "dev"
Requires-Dist: pydoc-markdown ; extra == "dev"
Project-URL: Bug Tracker, https://github.com/bitplane/yt-mpv/issues
Project-URL: Homepage, https://bitplane.net/dev/python/yt-mpv
Project-URL: Source Code, https://github.com/bitplane/yt-mpv
Provides-Extra: dev
